suppress.py
suppress-0.2.0.dist-info/LICENSE
suppress-0.2.0.dist-info/WHEEL
suppress-0.2.0.dist-info/METADATA
suppress-0.2.0.dist-info/RECORD
