Metadata-Version: 2.1
Name: suppress
Version: 0.2.0
Summary: A simple wrapper around contextlib.suppress
Author-email: j0hntv <j0hntvdesign@gmail.com>
Classifier: License :: OSI Approved :: MIT License
Project-URL: Home, https://github.com/j0hntv/suppress
